amoo_sina_lion/__init__.py
amoo_sina_lion/amoo_sina_lion.py
amoo_sina_lion-1.0.0.dist-info/METADATA
amoo_sina_lion-1.0.0.dist-info/WHEEL
amoo_sina_lion-1.0.0.dist-info/top_level.txt
amoo_sina_lion-1.0.0.dist-info/RECORD
