Metadata-Version: 2.1
Name: amoo_sina_lion
Version: 1.0.0
Summary: A test package for pydeploy students
Author: Sina Hosseini
Author-email: sshosseinivaez@gmail.com
